<haxe>
	<class path="Array" params="T" file="/usr/lib/haxe/std/Array.hx" extern="1">
		<length public="1" set="null">
			<x path="Int"/>
			<haxe_doc>The length of `this` Array.</haxe_doc>
		</length>
		<concat public="1" set="method">
			<f a="a">
				<c path="Array"><c path="Array.T"/></c>
				<c path="Array"><c path="Array.T"/></c>
			</f>
			<haxe_doc>Returns a new Array by appending the elements of `a` to the elements of
		`this` Array.

		This operation does not modify `this` Array.

		If `a` is the empty Array `[]`, a copy of `this` Array is returned.

		The length of the returned Array is equal to the sum of `this.length`
		and `a.length`.

		If `a` is `null`, the result is unspecified.</haxe_doc>
		</concat>
		<join public="1" set="method">
			<f a="sep">
				<c path="String"/>
				<c path="String"/>
			</f>
			<haxe_doc>Returns a string representation of `this` Array, with `sep` separating
		each element.

		The result of this operation is equal to `Std.string(this[0]) + sep +
		Std.string(this[1]) + sep + ... + sep + Std.string(this[this.length-1])`

		If `this` is the empty Array `[]`, the result is the empty String `""`.
		If `this` has exactly one element, the result is equal to a call to
		`Std.string(this[0])`.

		If `sep` is null, the result is unspecified.</haxe_doc>
		</join>
		<pop public="1" set="method">
			<f a=""><t path="Null"><c path="Array.T"/></t></f>
			<haxe_doc>Removes the last element of `this` Array and returns it.

		This operation modifies `this` Array in place.

		If `this` has at least one element, `this.length` will decrease by 1.

		If `this` is the empty Array `[]`, null is returned and the length
		remains 0.</haxe_doc>
		</pop>
		<push public="1" set="method">
			<f a="x">
				<c path="Array.T"/>
				<x path="Int"/>
			</f>
			<haxe_doc>Adds the element `x` at the end of `this` Array and returns the new
		length of `this` Array.

		This operation modifies `this` Array in place.

		`this.length` increases by 1.</haxe_doc>
		</push>
		<reverse public="1" set="method">
			<f a=""><x path="Void"/></f>
			<haxe_doc><![CDATA[Reverse the order of elements of `this` Array.

		This operation modifies `this` Array in place.

		If `this.length < 2`, `this` remains unchanged.]]></haxe_doc>
		</reverse>
		<shift public="1" set="method">
			<f a=""><t path="Null"><c path="Array.T"/></t></f>
			<haxe_doc>Removes the first element of `this` Array and returns it.

		This operation modifies `this` Array in place.

		If `this` has at least one element, `this`.length and the index of each
		remaining element is decreased by 1.

		If `this` is the empty Array `[]`, `null` is returned and the length
		remains 0.</haxe_doc>
		</shift>
		<slice public="1" set="method">
			<f a="pos:?end">
				<x path="Int"/>
				<x path="Int"/>
				<c path="Array"><c path="Array.T"/></c>
			</f>
			<haxe_doc>Creates a shallow copy of the range of `this` Array, starting at and
		including `pos`, up to but not including `end`.

		This operation does not modify `this` Array.

		The elements are not copied and retain their identity.

		If `end` is omitted or exceeds `this.length`, it defaults to the end of
		`this` Array.

		If `pos` or `end` are negative, their offsets are calculated from the
		end of `this` Array by `this.length + pos` and `this.length + end`
		respectively. If this yields a negative value, 0 is used instead.

		If `pos` exceeds `this.length` or if `end` is less than or equals
		`pos`, the result is `[]`.</haxe_doc>
		</slice>
		<sort public="1" set="method">
			<f a="f">
				<f a=":">
					<c path="Array.T"/>
					<c path="Array.T"/>
					<x path="Int"/>
				</f>
				<x path="Void"/>
			</f>
			<haxe_doc><![CDATA[Sorts `this` Array according to the comparison function `f`, where
		`f(x,y)` returns 0 if x == y, a positive Int if x > y and a
		negative Int if x < y.

		This operation modifies `this` Array in place.

		The sort operation is not guaranteed to be stable, which means that the
		order of equal elements may not be retained. For a stable Array sorting
		algorithm, `haxe.ds.ArraySort.sort()` can be used instead.

		If `f` is null, the result is unspecified.]]></haxe_doc>
		</sort>
		<splice public="1" set="method">
			<f a="pos:len">
				<x path="Int"/>
				<x path="Int"/>
				<c path="Array"><c path="Array.T"/></c>
			</f>
			<haxe_doc><![CDATA[Removes `len` elements from `this` Array, starting at and including
		`pos`, an returns them.

		This operation modifies `this` Array in place.

		If `len` is < 0 or `pos` exceeds `this`.length, the result is the empty
		Array [].

		If `pos` is negative, its value is calculated from the end	of `this`
		Array by `this.length + pos`. If this yields a negative value, 0 is
		used instead.

		If the sum of the resulting values for `len` and `pos` exceed
		`this.length`, this operation will affect the elements from `pos` to the
		end of `this` Array.

		The length of the returned Array is equal to the new length of `this`
		Array subtracted from the original length of `this` Array. In other
		words, each element of the original `this` Array either remains in
		`this` Array or becomes an element of the returned Array.]]></haxe_doc>
		</splice>
		<toString public="1" set="method">
			<f a=""><c path="String"/></f>
			<haxe_doc>Returns a string representation of `this` Array.

		The result will include the individual elements' String representations
		separated by comma. The enclosing [ ] may be missing on some platforms,
		use `Std.string()` to get a String representation that is consistent
		across platforms.</haxe_doc>
		</toString>
		<unshift public="1" set="method">
			<f a="x">
				<c path="Array.T"/>
				<x path="Void"/>
			</f>
			<haxe_doc>Adds the element `x` at the start of `this` Array.

		This operation modifies `this` Array in place.

		`this.length` and the index of each Array element increases by 1.</haxe_doc>
		</unshift>
		<insert public="1" set="method">
			<f a="pos:x">
				<x path="Int"/>
				<c path="Array.T"/>
				<x path="Void"/>
			</f>
			<haxe_doc>Inserts the element `x` at the position `pos`.

		This operation modifies `this` Array in place.

		The offset is calculated like so:

		- If `pos` exceeds `this.length`, the offset is `this.length`.
		- If `pos` is negative, the offset is calculated from the end of `this`
		  Array, i.e. `this.length + pos`. If this yields a negative value, the
		  offset is 0.
		- Otherwise, the offset is `pos`.

		If the resulting offset does not exceed `this.length`, all elements from
		and including that offset to the end of `this` Array are moved one index
		ahead.</haxe_doc>
		</insert>
		<remove public="1" set="method">
			<f a="x">
				<c path="Array.T"/>
				<x path="Bool"/>
			</f>
			<haxe_doc>Removes the first occurence of `x` in `this` Array.

		This operation modifies `this` Array in place.

		If `x` is found by checking standard equality, it is removed from `this`
		Array and all following elements are reindexed acoordingly. The function
		then returns true.

		If `x` is not found, `this` Array is not changed and the function
		returns false.</haxe_doc>
		</remove>
		<indexOf public="1" set="method">
			<f a="x:?fromIndex">
				<c path="Array.T"/>
				<x path="Int"/>
				<x path="Int"/>
			</f>
			<haxe_doc>Returns position of the first occurense of `x` in `this` Array, searching front to back.

		If `x` is found by checking standard equality, the function returns its index.

		If `x` is not found, the function returns -1.

		If `fromIndex` is specified, it will be used as the starting index to search from,
		otherwise search starts with zero index. If it is negative, it will be taken as the
		offset from the end of `this` Array to compute the starting index. If given or computed
		starting index is less than 0, the whole array will be searched, if it is greater than
		or equal to the length of `this` Array, the function returns -1.</haxe_doc>
		</indexOf>
		<lastIndexOf public="1" set="method">
			<f a="x:?fromIndex">
				<c path="Array.T"/>
				<x path="Int"/>
				<x path="Int"/>
			</f>
			<haxe_doc>Returns position of the last occurense of `x` in `this` Array, searching back to front.

		If `x` is found by checking standard equality, the function returns its index.

		If `x` is not found, the function returns -1.

		If `fromIndex` is specified, it will be used as the starting index to search from,
		otherwise search starts with the last element index. If it is negative, it will be
		taken as the offset from the end of `this` Array to compute the starting index. If
		given or computed starting index is greater than or equal to the length of `this` Array,
		the whole array will be searched, if it is less than 0, the function returns -1.</haxe_doc>
		</lastIndexOf>
		<copy public="1" set="method">
			<f a=""><c path="Array"><c path="Array.T"/></c></f>
			<haxe_doc>Returns a shallow copy of `this` Array.

		The elements are not copied and retain their identity, so
		`a[i] == a.copy()[i]` is true for any valid `i`. However,
		`a == a.copy()` is always false.</haxe_doc>
		</copy>
		<iterator public="1" set="method">
			<f a=""><t path="Iterator"><c path="Array.T"/></t></f>
			<haxe_doc>Returns an iterator of the Array values.</haxe_doc>
		</iterator>
		<map public="1" params="S" set="method">
			<f a="f">
				<f a="">
					<c path="Array.T"/>
					<c path="map.S"/>
				</f>
				<c path="Array"><c path="map.S"/></c>
			</f>
			<haxe_doc>Creates a new Array by applying function `f` to all elements of `this`.

		The order of elements is preserved.

		If `f` is null, the result is unspecified.</haxe_doc>
		</map>
		<filter public="1" set="method">
			<f a="f">
				<f a="">
					<c path="Array.T"/>
					<x path="Bool"/>
				</f>
				<c path="Array"><c path="Array.T"/></c>
			</f>
			<haxe_doc>Returns an Array containing those elements of `this` for which `f`
		returned true.

		The individual elements are not duplicated and retain their identity.

		If `f` is null, the result is unspecified.</haxe_doc>
		</filter>
		<new public="1" set="method">
			<f a=""><x path="Void"/></f>
			<haxe_doc>Creates a new Array.</haxe_doc>
		</new>
		<haxe_doc>An Array is a storage for values. You can access it using indexes or
	with its API.

	@see https://haxe.org/manual/std-Array.html
	@see https://haxe.org/manual/lf-array-comprehension.html</haxe_doc>
	</class>
	<abstract path="Class" params="T" file="/usr/lib/haxe/std/Class.hx">
		<this><x path="Class"><c path="Class.T"/></x></this>
		<haxe_doc>An abstract type that represents a Class.

	See `Type` for the Haxe Reflection API.

	@see https://haxe.org/manual/types-class-instance.html</haxe_doc>
		<meta>
			<m n=":coreType"/>
			<m n=":runtimeValue"/>
		</meta>
	</abstract>
	<abstract path="Enum" params="T" file="/usr/lib/haxe/std/Enum.hx">
		<this><x path="Enum"><c path="Enum.T"/></x></this>
		<haxe_doc>An abstract type that represents an Enum type.

	The corresponding enum instance type is `EnumValue`.

	See `Type` for the Haxe Reflection API.

	@see https://haxe.org/manual/types-enum-instance.html</haxe_doc>
		<meta>
			<m n=":coreType"/>
			<m n=":runtimeValue"/>
		</meta>
	</abstract>
	<abstract path="EnumValue" params="" file="/usr/lib/haxe/std/EnumValue.hx">
		<this><x path="EnumValue"/></this>
		<haxe_doc>An abstract type that represents any enum value.
	See `Type` for the Haxe Reflection API.

	@see https://haxe.org/manual/types-enum-instance.html</haxe_doc>
		<meta><m n=":coreType"/></meta>
	</abstract>
	<class path="List" params="T" file="/usr/lib/haxe/std/List.hx">
		<h><c path="_List.ListNode"><c path="List.T"/></c></h>
		<q><c path="_List.ListNode"><c path="List.T"/></c></q>
		<length public="1" set="null">
			<x path="Int"/>
			<haxe_doc>The length of `this` List.</haxe_doc>
		</length>
		<add public="1" set="method" line="52">
			<f a="item">
				<c path="List.T"/>
				<x path="Void"/>
			</f>
			<haxe_doc>Adds element `item` at the end of `this` List.

		`this.length` increases by 1.</haxe_doc>
		</add>
		<isEmpty public="1" set="method" line="113">
			<f a=""><x path="Bool"/></f>
			<haxe_doc>Tells if `this` List is empty.</haxe_doc>
		</isEmpty>
		<new public="1" set="method" line="43">
			<f a=""><x path="Void"/></f>
			<haxe_doc>Creates a new empty list.</haxe_doc>
		</new>
		<haxe_doc>A linked-list of elements. The list is composed of element container objects
	that are chained together. It is optimized so that adding or removing an
	element does not imply copying the whole list content every time.

	@see https://haxe.org/manual/std-List.html</haxe_doc>
		<meta>
			<m n=":keep"/>
			<m n=":directlyUsed"/>
		</meta>
	</class>
	<class path="_List.ListNode" params="T" file="/usr/lib/haxe/std/List.hx" private="1" module="List">
		<item public="1"><c path="_List.ListNode.T"/></item>
		<next public="1"><c path="_List.ListNode"><c path="_List.ListNode.T"/></c></next>
		<new public="1" set="method" line="255"><f a="item:next">
	<c path="_List.ListNode.T"/>
	<c path="_List.ListNode"><c path="_List.ListNode.T"/></c>
	<x path="Void"/>
</f></new>
		<meta>
			<m n=":keep"/>
			<m n=":directlyUsed"/>
		</meta>
	</class>
	<abstract path="Map" params="K:V" file="/usr/lib/haxe/std/Map.hx">
		<from>
			<icast field="fromStringMap"><c path="haxe.ds.StringMap"><c path="fromStringMap.V"/></c></icast>
			<icast field="fromIntMap"><c path="haxe.ds.IntMap"><c path="fromIntMap.V"/></c></icast>
			<icast field="fromObjectMap"><c path="haxe.ds.ObjectMap">
	<c path="fromObjectMap.K"/>
	<c path="fromObjectMap.V"/>
</c></icast>
		</from>
		<this><t path="IMap">
	<c path="Map.K"/>
	<c path="Map.V"/>
</t></this>
		<to>
			<icast field="toStringMap"><c path="haxe.ds.StringMap"><c path="toStringMap.V"/></c></icast>
			<icast field="toIntMap"><c path="haxe.ds.IntMap"><c path="toIntMap.V"/></c></icast>
			<icast field="toEnumValueMapMap"><c path="haxe.ds.EnumValueMap">
	<c path="toEnumValueMapMap.K"/>
	<c path="toEnumValueMapMap.V"/>
</c></icast>
			<icast field="toObjectMap"><c path="haxe.ds.ObjectMap">
	<c path="toObjectMap.K"/>
	<c path="toObjectMap.V"/>
</c></icast>
		</to>
		<haxe_doc><![CDATA[Map allows key to value mapping for arbitrary value types, and many key
	types.

	This is a multi-type abstract, it is instantiated as one of its
	specialization types depending on its type parameters.

	A Map can be instantiated without explicit type parameters. Type inference
	will then determine the type parameters from the usage.

	Maps can also be created with `key1 => value1, key2 => value2` syntax.

	Map is an abstract type, it is not available at runtime.

	@see https://haxe.org/manual/std-Map.html]]></haxe_doc>
		<meta><m n=":multiType"><e>@:followWithAbstracts K</e></m></meta>
		<impl><class path="_Map.Map_Impl_" params="" file="/usr/lib/haxe/std/Map.hx" private="1" module="Map"><meta>
	<m n=":keep"/>
	<m n=":final"/>
</meta></class></impl>
	</abstract>
	<typedef path="IMap" params="K:V" file="/usr/lib/haxe/std/Map.hx" module="Map">
		<c path="haxe.IMap">
			<c path="IMap.K"/>
			<c path="IMap.V"/>
		</c>
		<meta>
			<m n=":dox"><e>hide</e></m>
			<m n=":deprecated"/>
		</meta>
	</typedef>
	<class path="Reflect" params="" file="/usr/lib/haxe/std/Reflect.hx" extern="1">
		<hasField public="1" set="method" static="1">
			<f a="o:field">
				<d/>
				<c path="String"/>
				<x path="Bool"/>
			</f>
			<haxe_doc>Tells if structure `o` has a field named `field`.

		This is only guaranteed to work for anonymous structures. Refer to
		`Type.getInstanceFields` for a function supporting class instances.

		If `o` or `field` are null, the result is unspecified.</haxe_doc>
		</hasField>
		<field public="1" set="method" static="1">
			<f a="o:field">
				<d/>
				<c path="String"/>
				<d/>
			</f>
			<haxe_doc>Returns the value of the field named `field` on object `o`.

		If `o` is not an object or has no field named `field`, the result is
		null.

		If the field is defined as a property, its accessors are ignored. Refer
		to `Reflect.getProperty` for a function supporting property accessors.

		If `field` is null, the result is unspecified.

		(As3) If used on a property field, the getter will be invoked. It is
		not possible to obtain the value directly.</haxe_doc>
		</field>
		<setField public="1" set="method" static="1">
			<f a="o:field:value">
				<d/>
				<c path="String"/>
				<d/>
				<x path="Void"/>
			</f>
			<haxe_doc>Sets the field named `field` of object `o` to value `value`.

		If `o` has no field named `field`, this function is only guaranteed to
		work for anonymous structures.

		If `o` or `field` are null, the result is unspecified.

		(As3) If used on a property field, the setter will be invoked. It is
		not possible to set the value directly.</haxe_doc>
		</setField>
		<getProperty public="1" set="method" static="1">
			<f a="o:field">
				<d/>
				<c path="String"/>
				<d/>
			</f>
			<haxe_doc>Returns the value of the field named `field` on object `o`, taking
		property getter functions into account.

		If the field is not a property, this function behaves like
		`Reflect.field`, but might be slower.

		If `o` or `field` are null, the result is unspecified.</haxe_doc>
		</getProperty>
		<setProperty public="1" set="method" static="1">
			<f a="o:field:value">
				<d/>
				<c path="String"/>
				<d/>
				<x path="Void"/>
			</f>
			<haxe_doc>Sets the field named `field` of object `o` to value `value`, taking
		property setter functions into account.

		If the field is not a property, this function behaves like
		`Reflect.setField`, but might be slower.

		If `field` is null, the result is unspecified.</haxe_doc>
		</setProperty>
		<callMethod public="1" set="method" static="1">
			<f a="o:func:args">
				<d/>
				<x path="haxe.Function"/>
				<c path="Array"><d/></c>
				<d/>
			</f>
			<haxe_doc>Call a method with the given object and arguments.</haxe_doc>
		</callMethod>
		<fields public="1" set="method" static="1">
			<f a="o">
				<d/>
				<c path="Array"><c path="String"/></c>
			</f>
			<haxe_doc>Returns the fields of structure `o`.

		This method is only guaranteed to work on anonymous structures. Refer to
		`Type.getInstanceFields` for a function supporting class instances.

		If `o` is null, the result is unspecified.</haxe_doc>
		</fields>
		<isFunction public="1" set="method" static="1">
			<f a="f">
				<d/>
				<x path="Bool"/>
			</f>
			<haxe_doc>Returns true if `f` is a function, false otherwise.

		If `f` is null, the result is false.</haxe_doc>
		</isFunction>
		<compare public="1" params="T" set="method" static="1">
			<f a="a:b">
				<c path="compare.T"/>
				<c path="compare.T"/>
				<x path="Int"/>
			</f>
			<haxe_doc>Compares `a` and `b`.

		If `a` is less than `b`, the result is negative. If `b` is less than
		`a`, the result is positive. If `a` and `b` are equal, the result is 0.

		This function is only defined if `a` and `b` are of the same type.

		If that type is a function, the result is unspecified and
		`Reflect.compareMethods` should be used instead.

		For all other types, the result is 0 if `a` and `b` are equal. If they
		are not equal, the result depends on the type and is negative if:

		- Numeric types: a is less than b
		- String: a is lexicographically less than b
		- Other: unspecified

		If `a` and `b` are null, the result is 0. If only one of them is null,
		the result is unspecified.</haxe_doc>
		</compare>
		<compareMethods public="1" set="method" static="1">
			<f a="f1:f2">
				<d/>
				<d/>
				<x path="Bool"/>
			</f>
			<haxe_doc>Compares the functions `f1` and `f2`.

		If `f1` or `f2` are not functions, the result is unspecified.

		Otherwise the result is true if `f1` and the `f2` are physically equal,
		false otherwise.</haxe_doc>
		</compareMethods>
		<isObject public="1" set="method" static="1">
			<f a="v">
				<d/>
				<x path="Bool"/>
			</f>
			<haxe_doc><![CDATA[Tells if `v` is an object.

		The result is true if `v` is one of the following:

		- class instance
		- structure
		- `Class<T>`
		- `Enum<T>`

		Otherwise, including if `v` is null, the result is false.]]></haxe_doc>
		</isObject>
		<isEnumValue public="1" set="method" static="1">
			<f a="v">
				<d/>
				<x path="Bool"/>
			</f>
			<haxe_doc>Tells if `v` is an enum value.

		The result is true if `v` is of type EnumValue, i.e. an enum
		constructor.

		Otherwise, including if `v` is null, the result is false.</haxe_doc>
		</isEnumValue>
		<deleteField public="1" set="method" static="1">
			<f a="o:field">
				<d/>
				<c path="String"/>
				<x path="Bool"/>
			</f>
			<haxe_doc>Removes the field named `field` from structure `o`.

		This method is only guaranteed to work on anonymous structures.

		If `o` or `field` are null, the result is unspecified.</haxe_doc>
		</deleteField>
		<copy public="1" params="T" set="method" static="1">
			<f a="o">
				<c path="copy.T"/>
				<c path="copy.T"/>
			</f>
			<haxe_doc>Copies the fields of structure `o`.

		This is only guaranteed to work on anonymous structures.

		If `o` is null, the result is unspecified.</haxe_doc>
		</copy>
		<makeVarArgs public="1" set="method" static="1">
			<f a="f">
				<f a="">
					<c path="Array"><d/></c>
					<d/>
				</f>
				<d/>
			</f>
			<haxe_doc>Transform a function taking an array of arguments into a function that can
		be called with any number of arguments.</haxe_doc>
			<overloads><makeVarArgs public="1" set="method">
	<f a="f">
		<f a="">
			<c path="Array"><d/></c>
			<x path="Void"/>
		</f>
		<d/>
	</f>
	<haxe_doc>Transform a function taking an array of arguments into a function that can
		be called with any number of arguments.</haxe_doc>
</makeVarArgs></overloads>
		</makeVarArgs>
		<haxe_doc>The Reflect API is a way to manipulate values dynamically through an
	abstract interface in an untyped manner. Use with care.

	@see https://haxe.org/manual/std-reflection.html</haxe_doc>
		<meta><m n=":directlyUsed"/></meta>
	</class>
	<class path="Std" params="" file="/usr/lib/haxe/std/Std.hx" extern="1">
		<is public="1" set="method" static="1">
			<f a="v:t">
				<d/>
				<d/>
				<x path="Bool"/>
			</f>
			<haxe_doc>Tells if a value `v` is of the type `t`. Returns `false` if `v` or `t` are null.</haxe_doc>
		</is>
		<instance public="1" params="T:S" set="method" static="1">
			<f a="value:c">
				<c path="instance.T"/>
				<x path="Class"><c path="instance.S"/></x>
				<c path="instance.S"/>
			</f>
			<haxe_doc>Checks if object `value` is an instance of class `c`.

		Compiles only if the class specified by `c` can be assigned to the type
		of `value`.

		This method checks if a downcast is possible. That is, if the runtime
		type of `value` is assignable to the class specified by `c`, `value` is
		returned. Otherwise null is returned.

		This method is not guaranteed to work with interfaces or core types such
		as `String`, `Array` and `Date`.

		If `value` is null, the result is null. If `c` is null, the result is
		unspecified.</haxe_doc>
		</instance>
		<string public="1" set="method" static="1">
			<f a="s">
				<d/>
				<c path="String"/>
			</f>
			<haxe_doc>Converts any value to a String.

		If `s` is of `String`, `Int`, `Float` or `Bool`, its value is returned.

		If `s` is an instance of a class and that class or one of its parent classes has
		a `toString` method, that method is called. If no such method is present, the result
		is unspecified.

		If `s` is an enum constructor without argument, the constructor's name is returned. If
		arguments exists, the constructor's name followed by the String representations of
		the arguments is returned.

		If `s` is a structure, the field names along with their values are returned. The field order
		and the operator separating field names and values are unspecified.

		If s is null, "null" is returned.</haxe_doc>
		</string>
		<int public="1" set="method" static="1">
			<f a="x">
				<x path="Float"/>
				<x path="Int"/>
			</f>
			<haxe_doc>Converts a `Float` to an `Int`, rounded towards 0.

		If `x` is outside of the signed Int32 range, or is `NaN`, `NEGATIVE_INFINITY` or `POSITIVE_INFINITY`, the result is unspecified.</haxe_doc>
		</int>
		<parseInt public="1" set="method" static="1">
			<f a="x">
				<c path="String"/>
				<t path="Null"><x path="Int"/></t>
			</f>
			<haxe_doc>Converts a `String` to an `Int`.

		Leading whitespaces are ignored.

		If `x` starts with 0x or 0X, hexadecimal notation is recognized where the following digits may
		contain 0-9 and A-F.

		Otherwise `x` is read as decimal number with 0-9 being allowed characters. `x` may also start with
		a - to denote a negative value.

		In decimal mode, parsing continues until an invalid character is detected, in which case the
		result up to that point is returned. For hexadecimal notation, the effect of invalid characters
		is unspecified.

		Leading 0s that are not part of the 0x/0X hexadecimal notation are ignored, which means octal
		notation is not supported.

		If the input cannot be recognized, the result is `null`.</haxe_doc>
		</parseInt>
		<parseFloat public="1" set="method" static="1">
			<f a="x">
				<c path="String"/>
				<x path="Float"/>
			</f>
			<haxe_doc>Converts a `String` to a `Float`.

		The parsing rules for `parseInt` apply here as well, with the exception of invalid input
		resulting in a `NaN` value instead of null.

		Additionally, decimal notation may contain a single `.` to denote the start of the fractions.</haxe_doc>
		</parseFloat>
		<random public="1" set="method" static="1">
			<f a="x">
				<x path="Int"/>
				<x path="Int"/>
			</f>
			<haxe_doc><![CDATA[Return a random integer between 0 included and `x` excluded.

		If `x <= 1`, the result is always 0.]]></haxe_doc>
		</random>
		<haxe_doc>The Std class provides standard methods for manipulating basic types.</haxe_doc>
		<meta><m n=":directlyUsed"/></meta>
	</class>
	<abstract path="Void" params="" file="/usr/lib/haxe/std/StdTypes.hx" module="StdTypes">
		<this><x path="Void"/></this>
		<haxe_doc>The standard `Void` type. Only `null` values can be of the type `Void`.

	@see https://haxe.org/manual/types-void.html</haxe_doc>
		<meta><m n=":coreType"/></meta>
	</abstract>
	<abstract path="Float" params="" file="/usr/lib/haxe/std/StdTypes.hx" module="StdTypes">
		<this><x path="Float"/></this>
		<haxe_doc><![CDATA[The standard `Float` type, this is a double-precision IEEE 64bit float.

	On static targets, `null` cannot be assigned to Float. If this is necessary,
	`Null<Float>` can be used instead.

	`Std.int` converts a `Float` to an `Int`, rounded towards 0.
	`Std.parseFloat` converts a `String` to a `Float`.

	@see https://haxe.org/manual/types-basic-types.html
	@see https://haxe.org/manual/types-nullability.html]]></haxe_doc>
		<meta>
			<m n=":coreType"/>
			<m n=":notNull"/>
			<m n=":runtimeValue"/>
		</meta>
	</abstract>
	<abstract path="Int" params="" file="/usr/lib/haxe/std/StdTypes.hx" module="StdTypes">
		<this><x path="Int"/></this>
		<to><icast><x path="Float"/></icast></to>
		<haxe_doc><![CDATA[The standard `Int` type. Its precision depends on the platform.

	On static targets, `null` cannot be assigned to `Int`. If this is necessary,
	`Null<Int>` can be used instead.

	`Std.int` converts a `Float` to an `Int`, rounded towards 0.
	`Std.parseInt` converts a `String` to an `Int`.

	@see https://haxe.org/manual/types-basic-types.html
	@see https://haxe.org/manual/std-math-integer-math.html
	@see https://haxe.org/manual/types-nullability.html]]></haxe_doc>
		<meta>
			<m n=":coreType"/>
			<m n=":notNull"/>
			<m n=":runtimeValue"/>
		</meta>
	</abstract>
	<typedef path="Null" params="T" file="/usr/lib/haxe/std/StdTypes.hx" module="StdTypes">
		<c path="Null.T"/>
		<haxe_doc>`Null` can be useful in two cases. In order to document some methods
	that accept or can return a `null` value, or for the Flash compiler and AS3
	generator to distinguish between base values that can be `null` and others that
	can't.

	@see https://haxe.org/manual/types-nullability.html</haxe_doc>
	</typedef>
	<abstract path="Bool" params="" file="/usr/lib/haxe/std/StdTypes.hx" module="StdTypes">
		<this><x path="Bool"/></this>
		<haxe_doc><![CDATA[The standard Boolean type, which can either be `true` or `false`.

	On static targets, `null` cannot be assigned to `Bool`. If this is necessary,
	`Null<Bool>` can be used instead.

	@see https://haxe.org/manual/types-bool.html
	@see https://haxe.org/manual/types-nullability.html]]></haxe_doc>
		<meta>
			<m n=":coreType"/>
			<m n=":notNull"/>
			<m n=":runtimeValue"/>
		</meta>
	</abstract>
	<abstract path="Dynamic" params="T" file="/usr/lib/haxe/std/StdTypes.hx" module="StdTypes">
		<this><x path="Dynamic"><c path="Dynamic.T"/></x></this>
		<haxe_doc>`Dynamic` is a special type which is compatible with all other types.

	Use of `Dynamic` should be minimized as it prevents several compiler
	checks and optimizations. See `Any` type for a safer alternative for
	representing values of any type.

	@see https://haxe.org/manual/types-dynamic.html</haxe_doc>
		<meta>
			<m n=":coreType"/>
			<m n=":runtimeValue"/>
		</meta>
	</abstract>
	<typedef path="Iterator" params="T" file="/usr/lib/haxe/std/StdTypes.hx" module="StdTypes">
		<a>
			<next set="method">
				<f a=""><c path="Iterator.T"/></f>
				<haxe_doc>Returns the current item of the `Iterator` and advances to the next one.

		This method is not required to check `hasNext()` first. A call to this
		method while `hasNext()` is `false` yields unspecified behavior.

		On the other hand, iterators should not require a call to `hasNext()`
		before the first call to `next()` if an element is available.</haxe_doc>
			</next>
			<hasNext set="method">
				<f a=""><x path="Bool"/></f>
				<haxe_doc>Returns `false` if the iteration is complete, `true` otherwise.

		Usually iteration is considered to be complete if all elements of the
		underlying data structure were handled through calls to `next()`. However,
		in custom iterators any logic may be used to determine the completion
		state.</haxe_doc>
			</hasNext>
		</a>
		<haxe_doc>An `Iterator` is a structure that permits iteration over elements of type `T`.

	Any class with matching `hasNext()` and `next()` fields is considered an `Iterator`
	and can then be used e.g. in `for`-loops. This makes it easy to implement
	custom iterators.

	@see https://haxe.org/manual/lf-iterators.html</haxe_doc>
	</typedef>
	<typedef path="Iterable" params="T" file="/usr/lib/haxe/std/StdTypes.hx" module="StdTypes">
		<a><iterator set="method"><f a=""><t path="Iterator"><c path="Iterable.T"/></t></f></iterator></a>
		<haxe_doc>An `Iterable` is a data structure which has an `iterator()` method.
	See `Lambda` for generic functions on iterable structures.

	@see https://haxe.org/manual/lf-iterators.html</haxe_doc>
	</typedef>
	<class path="ArrayAccess" params="T" file="/usr/lib/haxe/std/StdTypes.hx" module="StdTypes" extern="1" interface="1"><haxe_doc>`ArrayAccess` is used to indicate a class that can be accessed using brackets.
	The type parameter represents the type of the elements stored.

	This interface should be used for externs only. Haxe does not support custom
	array access on classes. However, array access can be implemented for
	abstract types.

	@see https://haxe.org/manual/types-abstract-array-access.html</haxe_doc></class>
	<class path="String" params="" file="/usr/lib/haxe/std/String.hx" extern="1">
		<fromCharCode public="1" set="method" static="1">
			<f a="code">
				<x path="Int"/>
				<c path="String"/>
			</f>
			<haxe_doc>Returns the String corresponding to the character code `code`.

		If `code` is negative or has another invalid value, the result is
		unspecified.</haxe_doc>
		</fromCharCode>
		<length public="1" set="null">
			<x path="Int"/>
			<haxe_doc>The number of characters in `this` String.</haxe_doc>
		</length>
		<toUpperCase public="1" set="method">
			<f a=""><c path="String"/></f>
			<haxe_doc>Returns a String where all characters of `this` String are upper case.

		Affects the characters `a-z`. Other characters remain unchanged.</haxe_doc>
		</toUpperCase>
		<toLowerCase public="1" set="method">
			<f a=""><c path="String"/></f>
			<haxe_doc>Returns a String where all characters of `this` String are lower case.

		Affects the characters `A-Z`. Other characters remain unchanged.</haxe_doc>
		</toLowerCase>
		<charAt public="1" set="method">
			<f a="index">
				<x path="Int"/>
				<c path="String"/>
			</f>
			<haxe_doc>Returns the character at position `index` of `this` String.

		If `index` is negative or exceeds `this.length`, the empty String `""`
		is returned.</haxe_doc>
		</charAt>
		<charCodeAt public="1" set="method">
			<f a="index">
				<x path="Int"/>
				<t path="Null"><x path="Int"/></t>
			</f>
			<haxe_doc>Returns the character code at position `index` of `this` String.

		If `index` is negative or exceeds `this.length`, `null` is returned.

		To obtain the character code of a single character, `"x".code` can be
		used instead to inline the character code at compile time. Note that
		this only works on String literals of length 1.</haxe_doc>
		</charCodeAt>
		<indexOf public="1" set="method">
			<f a="str:?startIndex">
				<c path="String"/>
				<x path="Int"/>
				<x path="Int"/>
			</f>
			<haxe_doc>Returns the position of the leftmost occurence of `str` within `this`
		String.

		If `startIndex` is given, the search is performed within the substring
		of `this` String starting from `startIndex`. Otherwise the search is
		performed within `this` String. In either case, the returned position
		is relative to the beginning of `this` String.

		If `str` cannot be found, -1 is returned.</haxe_doc>
		</indexOf>
		<lastIndexOf public="1" set="method">
			<f a="str:?startIndex">
				<c path="String"/>
				<x path="Int"/>
				<x path="Int"/>
			</f>
			<haxe_doc>Returns the position of the rightmost occurence of `str` within `this`
		String.

		If `startIndex` is given, the search is performed within the substring
		of `this` String from 0 to `startIndex`. Otherwise the search is
		performed within `this` String. In either case, the returned position
		is relative to the beginning of `this` String.

		If `str` cannot be found, -1 is returned.</haxe_doc>
		</lastIndexOf>
		<split public="1" set="method">
			<f a="delimiter">
				<c path="String"/>
				<c path="Array"><c path="String"/></c>
			</f>
			<haxe_doc>Splits `this` String at each occurence of `delimiter`.

		If `this` String is the empty String `""`, the result is not consistent
		across targets and may either be `[]` (on Js, Cpp) or `[""]`.

		If `delimiter` is the empty String `""`, `this` String is split into an
		Array of `this.length` elements, where the elements correspond to the
		characters of `this` String.

		If `delimiter` is not found within `this` String, the result is an Array
		with one element, which equals `this` String.

		If `delimiter` is null, the result is unspecified.

		Otherwise, `this` String is split into parts at each occurence of
		`delimiter`. If `this` String starts (or ends) with `delimiter`, the
		result `Array` contains a leading (or trailing) empty String `""` element.
		Two subsequent delimiters also result in an empty String `""` element.</haxe_doc>
		</split>
		<substr public="1" set="method">
			<f a="pos:?len">
				<x path="Int"/>
				<x path="Int"/>
				<c path="String"/>
			</f>
			<haxe_doc>Returns `len` characters of `this` String, starting at position `pos`.

		If `len` is omitted, all characters from position `pos` to the end of
		`this` String are included.

		If `pos` is negative, its value is calculated from the end of `this`
		String by `this.length + pos`. If this yields a negative value, 0 is
		used instead.

		If the calculated position + `len` exceeds `this.length`, the characters
		from that position to the end of `this` String are returned.

		If `len` is negative, the result is unspecified.</haxe_doc>
		</substr>
		<substring public="1" set="method">
			<f a="startIndex:?endIndex">
				<x path="Int"/>
				<x path="Int"/>
				<c path="String"/>
			</f>
			<haxe_doc>Returns the part of `this` String from `startIndex` to but not including `endIndex`.

		If `startIndex` or `endIndex` are negative, 0 is used instead.

		If `startIndex` exceeds `endIndex`, they are swapped.

		If the (possibly swapped) `endIndex` is omitted or exceeds
		`this.length`, `this.length` is used instead.

		If the (possibly swapped) `startIndex` exceeds `this.length`, the empty
		String `""` is returned.</haxe_doc>
		</substring>
		<toString public="1" set="method">
			<f a=""><c path="String"/></f>
			<haxe_doc>Returns the String itself.</haxe_doc>
		</toString>
		<new public="1" set="method">
			<f a="string">
				<c path="String"/>
				<x path="Void"/>
			</f>
			<haxe_doc>Creates a copy from a given String.</haxe_doc>
		</new>
		<haxe_doc>The basic String class.

	A Haxe String is immutable, it is not possible to modify individual
	characters. No method of this class changes the state of `this` String.

	Strings can be constructed using the String literal syntax `"string value"`.

	String can be concatenated by using the `+` operator. If an operand is not a
	String, it is passed through `Std.string()` first.
	
	@see https://haxe.org/manual/std-String.html</haxe_doc>
		<meta><m n=":directlyUsed"/></meta>
	</class>
	<class path="StringBuf" params="" file="/usr/lib/haxe/std/StringBuf.hx">
		<b><c path="String"/></b>
		<length public="1" get="null" set="null">
			<x path="Int"/>
			<haxe_doc>The length of `this` StringBuf in characters.</haxe_doc>
		</length>
		<new public="1" get="inline" set="null" line="47">
			<f a=""><x path="Void"/></f>
			<haxe_doc>Creates a new StringBuf instance.

		This may involve initialization of the internal buffer.</haxe_doc>
		</new>
		<haxe_doc>A String buffer is an efficient way to build a big string by appending small
	elements together.

	Its cross-platform implementation uses String concatenation internally, but
	StringBuf may be optimized for different targets.

	Unlike String, an instance of StringBuf is not immutable in the sense that
	it can be passed as argument to functions which modify it by appending more
	values. However, the internal buffer cannot be modified.</haxe_doc>
		<meta>
			<m n=":keep"/>
			<m n=":directlyUsed"/>
		</meta>
	</class>
	<class path="Type" params="" file="/usr/lib/haxe/std/Type.hx" extern="1">
		<getClass public="1" params="T" set="method" static="1">
			<f a="o">
				<c path="getClass.T"/>
				<x path="Class"><c path="getClass.T"/></x>
			</f>
			<haxe_doc>Returns the class of `o`, if `o` is a class instance.

		If `o` is null or of a different type, null is returned.

		In general, type parameter information cannot be obtained at runtime.</haxe_doc>
		</getClass>
		<getEnum public="1" set="method" static="1">
			<f a="o">
				<x path="EnumValue"/>
				<x path="Enum"><d/></x>
			</f>
			<haxe_doc><![CDATA[Returns the enum of enum instance `o`.

		An enum instance is the result of using an enum constructor. Given an
		`enum Color { Red; }`, `getEnum(Red)` returns `Enum<Color>`.

		If `o` is null, null is returned.

		In general, type parameter information cannot be obtained at runtime.]]></haxe_doc>
		</getEnum>
		<getSuperClass public="1" set="method" static="1">
			<f a="c">
				<x path="Class"><d/></x>
				<x path="Class"><d/></x>
			</f>
			<haxe_doc>Returns the super-class of class `c`.

		If `c` has no super class, null is returned.

		If `c` is null, the result is unspecified.

		In general, type parameter information cannot be obtained at runtime.</haxe_doc>
		</getSuperClass>
		<getClassName public="1" set="method" static="1">
			<f a="c">
				<x path="Class"><d/></x>
				<c path="String"/>
			</f>
			<haxe_doc>Returns the name of class `c`, including its path.

		If `c` is inside a package, the package structure is returned dot-
		separated, with another dot separating the class name:
		`pack1.pack2.(...).packN.ClassName`
		If `c` is a sub-type of a Haxe module, that module is not part of the
		package structure.

		If `c` has no package, the class name is returned.

		If `c` is null, the result is unspecified.

		The class name does not include any type parameters.</haxe_doc>
		</getClassName>
		<getEnumName public="1" set="method" static="1">
			<f a="e">
				<x path="Enum"><d/></x>
				<c path="String"/>
			</f>
			<haxe_doc>Returns the name of enum `e`, including its path.

		If `e` is inside a package, the package structure is returned dot-
		separated, with another dot separating the enum name:
		`pack1.pack2.(...).packN.EnumName`
		If `e` is a sub-type of a Haxe module, that module is not part of the
		package structure.

		If `e` has no package, the enum name is returned.

		If `e` is null, the result is unspecified.

		The enum name does not include any type parameters.</haxe_doc>
		</getEnumName>
		<resolveClass public="1" set="method" static="1">
			<f a="name">
				<c path="String"/>
				<x path="Class"><d/></x>
			</f>
			<haxe_doc>Resolves a class by name.

		If `name` is the path of an existing class, that class is returned.

		Otherwise null is returned.

		If `name` is null or the path to a different type, the result is
		unspecified.

		The class name must not include any type parameters.</haxe_doc>
		</resolveClass>
		<resolveEnum public="1" set="method" static="1">
			<f a="name">
				<c path="String"/>
				<x path="Enum"><d/></x>
			</f>
			<haxe_doc>Resolves an enum by name.

		If `name` is the path of an existing enum, that enum is returned.

		Otherwise null is returned.

		If `name` is null the result is unspecified.

		If `name` is the path to a different type, null is returned.

		The enum name must not include any type parameters.</haxe_doc>
		</resolveEnum>
		<createInstance public="1" params="T" set="method" static="1">
			<f a="cl:args">
				<x path="Class"><c path="createInstance.T"/></x>
				<c path="Array"><d/></c>
				<c path="createInstance.T"/>
			</f>
			<haxe_doc>Creates an instance of class `cl`, using `args` as arguments to the
		class constructor.

		This function guarantees that the class constructor is called.

		Default values of constructors arguments are not guaranteed to be
		taken into account.

		If `cl` or `args` are null, or if the number of elements in `args` does
		not match the expected number of constructor arguments, or if any
		argument has an invalid type,  or if `cl` has no own constructor, the
		result is unspecified.

		In particular, default values of constructor arguments are not
		guaranteed to be taken into account.</haxe_doc>
		</createInstance>
		<createEmptyInstance public="1" params="T" set="method" static="1">
			<f a="cl">
				<x path="Class"><c path="createEmptyInstance.T"/></x>
				<c path="createEmptyInstance.T"/>
			</f>
			<haxe_doc>Creates an instance of class `cl`.

		This function guarantees that the class constructor is not called.

		If `cl` is null, the result is unspecified.</haxe_doc>
		</createEmptyInstance>
		<createEnum public="1" params="T" set="method" static="1">
			<f a="e:constr:?params">
				<x path="Enum"><c path="createEnum.T"/></x>
				<c path="String"/>
				<c path="Array"><d/></c>
				<c path="createEnum.T"/>
			</f>
			<haxe_doc>Creates an instance of enum `e` by calling its constructor `constr` with
		arguments `params`.

		If `e` or `constr` is null, or if enum `e` has no constructor named
		`constr`, or if the number of elements in `params` does not match the
		expected number of constructor arguments, or if any argument has an
		invalid type, the result is unspecified.</haxe_doc>
		</createEnum>
		<createEnumIndex public="1" params="T" set="method" static="1">
			<f a="e:index:?params">
				<x path="Enum"><c path="createEnumIndex.T"/></x>
				<x path="Int"/>
				<c path="Array"><d/></c>
				<c path="createEnumIndex.T"/>
			</f>
			<haxe_doc>Creates an instance of enum `e` by calling its constructor number
		`index` with arguments `params`.

		The constructor indices are preserved from Haxe syntax, so the first
		declared is index 0, the next index 1 etc.

		If `e` or `constr` is null, or if enum `e` has no constructor named
		`constr`, or if the number of elements in `params` does not match the
		expected number of constructor arguments, or if any argument has an
		invalid type, the result is unspecified.</haxe_doc>
		</createEnumIndex>
		<getInstanceFields public="1" set="method" static="1">
			<f a="c">
				<x path="Class"><d/></x>
				<c path="Array"><c path="String"/></c>
			</f>
			<haxe_doc>Returns a list of the instance fields of class `c`.

		This only includes fields which are known at compile-time. In
		particular, using getInstanceFields(getClass(obj)) will not include
		any fields which were added to obj at runtime.

		The order of the fields in the returned Array is unspecified.

		If `c` is null, the result is unspecified.

		(As3) This method only returns instance fields that are public.</haxe_doc>
		</getInstanceFields>
		<getClassFields public="1" set="method" static="1">
			<f a="c">
				<x path="Class"><d/></x>
				<c path="Array"><c path="String"/></c>
			</f>
			<haxe_doc>Returns a list of static fields of class `c`.

		This does not include static fields of parent classes.

		The order of the fields in the returned Array is unspecified.

		If `c` is null, the result is unspecified.

		(As3) This method only returns class fields that are public.</haxe_doc>
		</getClassFields>
		<getEnumConstructs public="1" set="method" static="1">
			<f a="e">
				<x path="Enum"><d/></x>
				<c path="Array"><c path="String"/></c>
			</f>
			<haxe_doc>Returns a list of the names of all constructors of enum `e`.

		The order of the constructor names in the returned Array is preserved
		from the original syntax.

		If `c` is null, the result is unspecified.</haxe_doc>
		</getEnumConstructs>
		<typeof public="1" set="method" static="1">
			<f a="v">
				<d/>
				<e path="ValueType"/>
			</f>
			<haxe_doc>Returns the runtime type of value `v`.

		The result corresponds to the type `v` has at runtime, which may vary
		per platform. Assumptions regarding this should be minimized to avoid
		surprises.</haxe_doc>
		</typeof>
		<enumEq public="1" params="T" set="method" static="1">
			<f a="a:b">
				<c path="enumEq.T"/>
				<c path="enumEq.T"/>
				<x path="Bool"/>
			</f>
			<haxe_doc>Recursively compares two enum instances `a` and `b` by value.

		Unlike `a == b`, this function performs a deep equality check on the
		arguments of the constructors, if exists.

		If `a` or `b` are null, the result is unspecified.</haxe_doc>
		</enumEq>
		<enumConstructor public="1" set="method" static="1">
			<f a="e">
				<x path="EnumValue"/>
				<c path="String"/>
			</f>
			<haxe_doc>Returns the constructor name of enum instance `e`.

		The result String does not contain any constructor arguments.

		If `e` is null, the result is unspecified.</haxe_doc>
		</enumConstructor>
		<enumParameters public="1" set="method" static="1">
			<f a="e">
				<x path="EnumValue"/>
				<c path="Array"><d/></c>
			</f>
			<haxe_doc>Returns a list of the constructor arguments of enum instance `e`.

		If `e` has no arguments, the result is [].

		Otherwise the result are the values that were used as arguments to `e`,
		in the order of their declaration.

		If `e` is null, the result is unspecified.</haxe_doc>
		</enumParameters>
		<enumIndex public="1" set="method" static="1">
			<f a="e">
				<x path="EnumValue"/>
				<x path="Int"/>
			</f>
			<haxe_doc>Returns the index of enum instance `e`.

		This corresponds to the original syntactic position of `e`. The index of
		the first declared constructor is 0, the next one is 1 etc.

		If `e` is null, the result is unspecified.</haxe_doc>
		</enumIndex>
		<allEnums public="1" params="T" set="method" static="1">
			<f a="e">
				<x path="Enum"><c path="allEnums.T"/></x>
				<c path="Array"><c path="allEnums.T"/></c>
			</f>
			<haxe_doc>Returns a list of all constructors of enum `e` that require no
		arguments.

		This may return the empty Array `[]` if all constructors of `e` require
		arguments.

		Otherwise an instance of `e` constructed through each of its non-
		argument constructors is returned, in the order of the constructor
		declaration.

		If `e` is null, the result is unspecified.</haxe_doc>
		</allEnums>
		<haxe_doc>The Haxe Reflection API allows retrieval of type information at runtime.

	This class complements the more lightweight Reflect class, with a focus on
	class and enum instances.

	@see https://haxe.org/manual/types.html
	@see https://haxe.org/manual/std-reflection.html</haxe_doc>
		<meta><m n=":directlyUsed"/></meta>
	</class>
	<typedef path="_XSPFPlaylist.Extension" params="" file="src/XSPFPlaylist.hx" private="1" module="XSPFPlaylist">
		<a>
			<content><c path="Xml"/></content>
			<application><c path="String"/></application>
		</a>
		<haxe_doc>The extension element allows non-XSPF XML to be included in XSPF documents.
	The purpose is to allow nested XML, which the meta and link elements do not.</haxe_doc>
	</typedef>
	<typedef path="_XSPFPlaylist.Link" params="" file="src/XSPFPlaylist.hx" private="1" module="XSPFPlaylist">
		<a>
			<rel><c path="String"/></rel>
			<content><c path="String"/></content>
		</a>
		<haxe_doc>The link element allows XSPF to be extended without the use of XML namespaces.</haxe_doc>
	</typedef>
	<typedef path="_XSPFPlaylist.Meta" params="" file="src/XSPFPlaylist.hx" private="1" module="XSPFPlaylist">
		<a>
			<rel><c path="String"/></rel>
			<content><c path="String"/></content>
		</a>
		<haxe_doc>The meta element allows metadata fields to be added to xspf:track elements.
	xspf:track elements MAY contain zero or more meta elements.</haxe_doc>
	</typedef>
	<class path="XSPFTrack" params="" file="src/XSPFPlaylist.hx" module="XSPFPlaylist">
		<parse public="1" set="method" line="163" static="1"><f a="x">
	<c path="Xml"/>
	<c path="XSPFTrack"/>
</f></parse>
		<location public="1">
			<c path="List"><c path="String"/></c>
			<haxe_doc>URI of resource to be rendered.
	 	Probably an audio resource, but MAY be any type of resource with a well-known duration,
	 	such as video, a SMIL document, or an XSPF document.
	 	The duration of the resource defined in this element defines the duration of rendering.
	 	xspf:track elements MAY contain zero or more location elements,
	 	but a user-agent MUST NOT render more than one of the named resources.</haxe_doc>
		</location>
		<identifier public="1">
			<c path="String"/>
			<haxe_doc>Canonical ID for this resource.
	 	Likely to be a hash or other location-independent name, such as a MusicBrainz identifier
	 	or isbn URN (if there existed isbn numbers for audio). MUST be a legal URI.</haxe_doc>
		</identifier>
		<title public="1">
			<c path="String"/>
			<haxe_doc>Name of the track that authored the resource which defines the duration of track rendering.
		This value is primarily for fuzzy lookups, though a user-agent may display it.</haxe_doc>
		</title>
		<creator public="1">
			<c path="String"/>
			<haxe_doc>Human-readable name of the entity (author, authors, group, company, etc) that authored the
		resource which defines the duration of track rendering.
		This value is primarily for fuzzy lookups, though a user-agent may display it.</haxe_doc>
		</creator>
		<annotation public="1">
			<c path="String"/>
			<haxe_doc>A human-readable comment on the track in text/plain format.</haxe_doc>
		</annotation>
		<info public="1">
			<c path="String"/>
			<haxe_doc>URI of a place where this resource can be bought or more info can be found.</haxe_doc>
		</info>
		<image public="1">
			<c path="String"/>
			<haxe_doc>URI of an image to display for the duration of the track.</haxe_doc>
		</image>
		<album public="1">
			<c path="String"/>
			<haxe_doc>Name of the collection from which the resource which defines the duration of track
		rendering comes. For a song originally published as a part of a CD or LP, this would
	 	be the title of the original release. This value is primarily for fuzzy lookups, though
	  	a user-agent may display it.</haxe_doc>
		</album>
		<trackNum public="1">
			<c path="String"/>
			<haxe_doc>Integer with value greater than zero giving the ordinal position of the media on the
	 	xspf:album. This value is primarily for fuzzy lookups, though a user-agent may display it.
	 	xspf:track elements MAY contain exactly one.
	 	It MUST be a valid XML Schema nonNegativeInteger.</haxe_doc>
		</trackNum>
		<duration public="1">
			<t path="Null"><x path="Int"/></t>
			<haxe_doc>The time to render a resource, in milliseconds.
	 	It MUST be a valid XML Schema nonNegativeInteger.
	 	This value is only a hint -- different XSPF generators will generate slightly different
	 	values. A user-agent MUST NOT use this value to determine the rendering duration, since the
	 	data will likely be low quality. xspf:track elements MAY contain exactly one duration element.</haxe_doc>
		</duration>
		<link public="1">
			<c path="List"><t path="_XSPFPlaylist.Link"/></c>
			<haxe_doc>* The link element allows XSPF to be extended without the use of XML namespaces. 
	 * xspf:track elements MAY contain zero or more link elements.</haxe_doc>
		</link>
		<meta public="1">
			<c path="List"><t path="_XSPFPlaylist.Meta"/></c>
			<haxe_doc>The meta element allows metadata fields to be added to xspf:track elements.
	 	xspf:track elements MAY contain zero or more meta elements.</haxe_doc>
		</meta>
		<extension public="1">
			<c path="List"><t path="_XSPFPlaylist.Extension"/></c>
			<haxe_doc>The extension element allows non-XSPF XML to be included in XSPF documents.
	 	The purpose is to allow nested XML, which the meta and link elements do not.</haxe_doc>
		</extension>
		<toXml public="1" set="method" line="125"><f a=""><c path="Xml"/></f></toXml>
		<new public="1" set="method" line="118"><f a=""><x path="Void"/></f></new>
		<meta><m n=":directlyUsed"/></meta>
	</class>
	<class path="XSPFTracklist" params="" file="src/XSPFPlaylist.hx" module="XSPFPlaylist">
		<extends path="List"><c path="XSPFTrack"/></extends>
		<parse public="1" set="method" line="197" static="1"><f a="x">
	<c path="Xml"/>
	<c path="XSPFTracklist"/>
</f></parse>
		<toXml public="1" set="method" line="191"><f a=""><c path="Xml"/></f></toXml>
		<new public="1" set="method" line="189"><f a=""><x path="Void"/></f></new>
		<meta><m n=":directlyUsed"/></meta>
	</class>
	<class path="XSPFPlaylist" params="" file="src/XSPFPlaylist.hx">
		<XMLNS public="1" get="inline" set="null" line="209" static="1">
			<c path="String"/>
			<haxe_doc>XML namespace</haxe_doc>
		</XMLNS>
		<VERSION public="1" get="inline" set="null" line="212" static="1">
			<c path="String"/>
			<haxe_doc>XSPF playlist version</haxe_doc>
		</VERSION>
		<MAX_ATTRIBUTION public="1" get="inline" set="null" line="215" static="1">
			<x path="Int"/>
			<haxe_doc>The max count of attribution elements</haxe_doc>
		</MAX_ATTRIBUTION>
		<parse public="1" set="method" line="337" static="1"><f a="x">
	<c path="Xml"/>
	<c path="XSPFPlaylist"/>
</f></parse>
		<attach public="1" set="method" line="364" static="1"><f a="x:src:name">
	<c path="Xml"/>
	<d/>
	<c path="String"/>
	<x path="Void"/>
</f></attach>
		<createElement public="1" set="method" line="369" static="1"><f a="name:content">
	<c path="String"/>
	<c path="String"/>
	<c path="Xml"/>
</f></createElement>
		<title public="1">
			<c path="String"/>
			<haxe_doc>Title for the playlist.</haxe_doc>
		</title>
		<creator public="1">
			<c path="String"/>
			<haxe_doc>Name of the entity (author, authors, group, company, etc) that authored the playlist.</haxe_doc>
		</creator>
		<annotation public="1">
			<c path="String"/>
			<haxe_doc>A human-readable comment on the playlist.
	 	This is character data, not HTML, and it may not contain markup. 
	 	xspf:playlist elements MAY contain exactly one.</haxe_doc>
		</annotation>
		<info public="1">
			<c path="String"/>
			<haxe_doc>URI of a web page to find out more about this playlist.
		Likely to be homepage of the author, and would be used to find out more about the
		author and to find more playlists by the author.</haxe_doc>
		</info>
		<location public="1">
			<c path="String"/>
			<haxe_doc>Source URI for this playlist.
		xspf:playlist elements MAY contain exactly one.</haxe_doc>
		</location>
		<identifier public="1">
			<c path="String"/>
			<haxe_doc>Canonical ID for this playlist.
		Likely to be a hash or other location-independent name.
		MUST be a legal URI.
		xspf:playlist elements MAY contain exactly one</haxe_doc>
		</identifier>
		<image public="1">
			<c path="String"/>
			<haxe_doc>URI of an image to display in the absence of a //playlist/trackList/image element.</haxe_doc>
		</image>
		<date public="1">
			<c path="String"/>
			<haxe_doc><![CDATA[Creation date (not last-modified date) of the playlist, formatted as a <a href=http://www.w3.org/TR/xmlschema-2/#dateTime>XML schema dateTime.</a>]]></haxe_doc>
		</date>
		<license public="1">
			<c path="String"/>
			<haxe_doc>URI of a resource that describes the license under which this playlist was released.</haxe_doc>
		</license>
		<attribution public="1">
			<c path="Xml"/>
			<haxe_doc>An ordered list of URIs.
		The purpose is to satisfy licenses allowing modification but requiring attribution.
		If you modify such a playlist, move its //playlist/location or //playlist/identifier
		element to the top of the items in the //playlist/attribution element.
		xspf:playlist elements MAY contain exactly one xspf:attribution element.
		Such a list can grow without limit, so as a practical matter we suggest deleting ancestors
		more than ten generations back.</haxe_doc>
		</attribution>
		<link public="1">
			<c path="List"><t path="_XSPFPlaylist.Link"/></c>
			<haxe_doc>The link element allows non-XSPF web resources to be included in XSPF documents
		without breaking XSPF validation. 
		xspf:playlist elements MAY contain zero or more link elements.</haxe_doc>
		</link>
		<meta public="1">
			<c path="List"><t path="_XSPFPlaylist.Meta"/></c>
			<haxe_doc>The meta element allows metadata fields to be added to XSPF.</haxe_doc>
		</meta>
		<tracklist public="1">
			<c path="XSPFTracklist"/>
			<haxe_doc>Ordered list of xspf:track elements to be rendered.
		The sequence is a hint, not a requirement; renderers are advised to play tracks from top
		to bottom unless there is an indication otherwise.
		If an xspf:track element cannot be rendered, a user-agent MUST skip to the next xspf:track
		element and MUST NOT interrupt the sequence.</haxe_doc>
		</tracklist>
		<toXml public="1" set="method" line="304"><f a=""><c path="Xml"/></f></toXml>
		<new public="1" set="method" line="299"><f a=""><x path="Void"/></f></new>
		<meta><m n=":directlyUsed"/></meta>
	</class>
	<abstract path="XmlType" params="" file="/usr/lib/haxe/std/Xml.hx" module="Xml">
		<this><x path="Int"/></this>
		<haxe_doc>Xml node types.

	@see https://haxe.org/manual/std-Xml.html</haxe_doc>
		<meta><m n=":enum"/></meta>
		<impl><class path="_Xml.XmlType_Impl_" params="" file="/usr/lib/haxe/std/Xml.hx" private="1" module="Xml"><meta>
	<m n=":keep"/>
	<m n=":final"/>
	<m n=":enum"/>
</meta></class></impl>
	</abstract>
	<class path="Xml" params="" file="/usr/lib/haxe/std/Xml.hx">
		<Element public="1" set="null" line="68" static="1">
			<x path="XmlType"/>
			<haxe_doc>XML element type.</haxe_doc>
		</Element>
		<PCData public="1" set="null" line="72" static="1">
			<x path="XmlType"/>
			<haxe_doc>XML parsed character data type.</haxe_doc>
		</PCData>
		<CData public="1" set="null" line="76" static="1">
			<x path="XmlType"/>
			<haxe_doc>XML character data type.</haxe_doc>
		</CData>
		<Comment public="1" set="null" line="80" static="1">
			<x path="XmlType"/>
			<haxe_doc>XML comment type.</haxe_doc>
		</Comment>
		<DocType public="1" set="null" line="84" static="1">
			<x path="XmlType"/>
			<haxe_doc>XML doctype element type.</haxe_doc>
		</DocType>
		<ProcessingInstruction public="1" set="null" line="88" static="1">
			<x path="XmlType"/>
			<haxe_doc>XML processing instruction type.</haxe_doc>
		</ProcessingInstruction>
		<Document public="1" set="null" line="92" static="1">
			<x path="XmlType"/>
			<haxe_doc>XML document type.</haxe_doc>
		</Document>
		<parse public="1" set="method" line="97" static="1">
			<f a="str">
				<c path="String"/>
				<c path="Xml"/>
			</f>
			<haxe_doc>Parses the String into an Xml document.</haxe_doc>
		</parse>
		<createElement public="1" set="method" line="158" static="1">
			<f a="name">
				<c path="String"/>
				<c path="Xml"/>
			</f>
			<haxe_doc>Creates a node of the given type.</haxe_doc>
		</createElement>
		<createPCData public="1" set="method" line="167" static="1">
			<f a="data">
				<c path="String"/>
				<c path="Xml"/>
			</f>
			<haxe_doc>Creates a node of the given type.</haxe_doc>
		</createPCData>
		<createCData public="1" set="method" line="176" static="1">
			<f a="data">
				<c path="String"/>
				<c path="Xml"/>
			</f>
			<haxe_doc>Creates a node of the given type.</haxe_doc>
		</createCData>
		<createComment public="1" set="method" line="185" static="1">
			<f a="data">
				<c path="String"/>
				<c path="Xml"/>
			</f>
			<haxe_doc>Creates a node of the given type.</haxe_doc>
		</createComment>
		<createDocType public="1" set="method" line="194" static="1">
			<f a="data">
				<c path="String"/>
				<c path="Xml"/>
			</f>
			<haxe_doc>Creates a node of the given type.</haxe_doc>
		</createDocType>
		<createProcessingInstruction public="1" set="method" line="203" static="1">
			<f a="data">
				<c path="String"/>
				<c path="Xml"/>
			</f>
			<haxe_doc>Creates a node of the given type.</haxe_doc>
		</createProcessingInstruction>
		<createDocument public="1" set="method" line="212" static="1">
			<f a=""><c path="Xml"/></f>
			<haxe_doc>Creates a node of the given type.</haxe_doc>
		</createDocument>
		<nodeType public="1" set="null">
			<x path="XmlType"/>
			<haxe_doc>Returns the type of the Xml Node. This should be used before
		accessing other functions since some might raise an exception
		if the node type is not correct.</haxe_doc>
		</nodeType>
		<nodeName public="1" get="null" set="null">
			<c path="String"/>
			<meta><m n=":isVar"/></meta>
			<haxe_doc>Returns the node name of an Element.</haxe_doc>
		</nodeName>
		<nodeValue public="1" get="null" set="null">
			<c path="String"/>
			<meta><m n=":isVar"/></meta>
			<haxe_doc>Returns the node value. Only works if the Xml node is not an Element or a Document.</haxe_doc>
		</nodeValue>
		<parent public="1" set="null">
			<c path="Xml"/>
			<haxe_doc>Returns the parent object in the Xml hierarchy.
		The parent can be `null`, an Element or a Document.</haxe_doc>
		</parent>
		<children><c path="Array"><c path="Xml"/></c></children>
		<attributeMap><x path="Map">
	<c path="String"/>
	<c path="String"/>
</x></attributeMap>
		<get public="1" set="method" line="220">
			<f a="att">
				<c path="String"/>
				<c path="String"/>
			</f>
			<haxe_doc>Get the given attribute of an Element node. Returns `null` if not found.
		Attributes are case-sensitive.</haxe_doc>
		</get>
		<set public="1" set="method" line="231">
			<f a="att:value">
				<c path="String"/>
				<c path="String"/>
				<x path="Void"/>
			</f>
			<haxe_doc>Set the given attribute value for an Element node.
		Attributes are case-sensitive.</haxe_doc>
		</set>
		<exists public="1" set="method" line="253">
			<f a="att">
				<c path="String"/>
				<x path="Bool"/>
			</f>
			<haxe_doc>Tells if the Element node has a given attribute.
		Attributes are case-sensitive.</haxe_doc>
		</exists>
		<elements public="1" set="method" line="283">
			<f a=""><t path="Iterator"><c path="Xml"/></t></f>
			<haxe_doc>Returns an iterator of all child nodes which are Elements.
		Only works if the current node is an Element or a Document.</haxe_doc>
		</elements>
		<firstElement public="1" set="method" line="310">
			<f a=""><c path="Xml"/></f>
			<haxe_doc>Returns the first child node which is an Element.</haxe_doc>
		</firstElement>
		<addChild public="1" set="method" line="326">
			<f a="x">
				<c path="Xml"/>
				<x path="Void"/>
			</f>
			<haxe_doc>Adds a child node to the Document or Element.
		A child node can only be inside one given parent node, which is indicated by the `parent` property.
		If the child is already inside this Document or Element, it will be moved to the last position among the Document or Element's children.
		If the child node was previously inside a different node, it will be moved to this Document or Element.</haxe_doc>
		</addChild>
		<removeChild public="1" set="method" line="339">
			<f a="x">
				<c path="Xml"/>
				<x path="Bool"/>
			</f>
			<haxe_doc>Removes a child from the Document or Element.
		Returns true if the child was successfuly removed.</haxe_doc>
		</removeChild>
		<new set="method" line="370"><f a="nodeType">
	<x path="XmlType"/>
	<x path="Void"/>
</f></new>
		<haxe_doc>Crossplatform Xml API.

	@see https://haxe.org/manual/std-Xml.html</haxe_doc>
		<meta>
			<m n=":keep"/>
			<m n=":directlyUsed"/>
		</meta>
	</class>
	<abstract path="haxe.Function" params="" file="/usr/lib/haxe/std/haxe/Constraints.hx" module="haxe.Constraints">
		<this><d/></this>
		<haxe_doc>This type unifies with any function type.

	It is intended to be used as a type parameter constraint. If used as a real
	type, the underlying type will be `Dynamic`.</haxe_doc>
		<meta><m n=":callable"/></meta>
		<impl><class path="haxe._Constraints.Function_Impl_" params="" file="/usr/lib/haxe/std/haxe/Constraints.hx" private="1" module="haxe.Constraints"><meta>
	<m n=":keep"/>
	<m n=":final"/>
</meta></class></impl>
	</abstract>
	<abstract path="haxe.FlatEnum" params="" file="/usr/lib/haxe/std/haxe/Constraints.hx" module="haxe.Constraints">
		<this><d/></this>
		<haxe_doc>This type unifies with an enum instance if all constructors of the enum
	require no arguments.

	It is intended to be used as a type parameter constraint. If used as a real
	type, the underlying type will be `Dynamic`.</haxe_doc>
		<impl><class path="haxe._Constraints.FlatEnum_Impl_" params="" file="/usr/lib/haxe/std/haxe/Constraints.hx" private="1" module="haxe.Constraints"><meta>
	<m n=":keep"/>
	<m n=":final"/>
</meta></class></impl>
	</abstract>
	<abstract path="haxe.Constructible" params="T" file="/usr/lib/haxe/std/haxe/Constraints.hx" module="haxe.Constraints">
		<this><d/></this>
		<haxe_doc><![CDATA[This type unifies with any instance of classes that have a constructor
	which
		* is public and
		* unifies with the type used for type parameter `T`.

	If a type parameter A is assigned to a type parameter B which is constrained
	to `Constructible<T>`, A must be explicitly constrained to
	`Constructible<T>` as well.

	It is intended to be used as a type parameter constraint. If used as a real
	type, the underlying type will be `Dynamic`.]]></haxe_doc>
		<impl><class path="haxe._Constraints.Constructible_Impl_" params="" file="/usr/lib/haxe/std/haxe/Constraints.hx" private="1" module="haxe.Constraints"><meta>
	<m n=":keep"/>
	<m n=":final"/>
</meta></class></impl>
	</abstract>
	<class path="haxe.IMap" params="K:V" file="/usr/lib/haxe/std/haxe/Constraints.hx" module="haxe.Constraints" interface="1"><meta><m n=":keep"/></meta></class>
	<class path="haxe.EnumTools" params="" file="/usr/lib/haxe/std/haxe/EnumTools.hx" extern="1">
		<getName public="1" params="T" get="inline" set="null" line="50" static="1">
			<f a="e">
				<x path="Enum"><c path="getName.T"/></x>
				<c path="String"/>
			</f>
			<haxe_doc>Returns the name of enum `e`, including its path.

		If `e` is inside a package, the package structure is returned dot-
		separated, with another dot separating the enum name:
			pack1.pack2.(...).packN.EnumName
		If `e` is a sub-type of a Haxe module, that module is not part of the
		package structure.

		If `e` has no package, the enum name is returned.

		If `e` is `null`, the result is unspecified.

		The enum name does not include any type parameters.</haxe_doc>
		</getName>
		<createByName public="1" params="T" get="inline" set="null" line="63" static="1">
			<f a="e:constr:?params">
				<x path="Enum"><c path="createByName.T"/></x>
				<c path="String"/>
				<c path="Array"><d/></c>
				<c path="createByName.T"/>
			</f>
			<haxe_doc>Creates an instance of enum `e` by calling its constructor `constr` with
		arguments `params`.

		If `e` or `constr` is `null`, or if enum `e` has no constructor named
		`constr`, or if the number of elements in `params` does not match the
		expected number of constructor arguments, or if any argument has an
		invalid type, the result is unspecified.</haxe_doc>
		</createByName>
		<createByIndex public="1" params="T" get="inline" set="null" line="79" static="1">
			<f a="e:index:?params">
				<x path="Enum"><c path="createByIndex.T"/></x>
				<x path="Int"/>
				<c path="Array"><d/></c>
				<c path="createByIndex.T"/>
			</f>
			<haxe_doc>Creates an instance of enum `e` by calling its constructor number
		`index` with arguments `params`.

		The constructor indices are preserved from Haxe syntax, so the first
		declared is index 0, the next index 1 etc.

		If `e` or `index` is `null`, or if enum `e` has no constructor
		corresponding to index `index`, or if the number of elements in `params`
		does not match the expected number of constructor arguments, or if any
		argument has an invalid type, the result is unspecified.</haxe_doc>
		</createByIndex>
		<createAll public="1" params="T" get="inline" set="null" line="96" static="1">
			<f a="e">
				<x path="Enum"><c path="createAll.T"/></x>
				<c path="Array"><c path="createAll.T"/></c>
			</f>
			<haxe_doc>Returns a list of all constructors of enum `e` that require no
		arguments.

		This may return the empty Array `[]` if all constructors of `e` require
		arguments.

		Otherwise an instance of `e` constructed through each of its non-
		argument constructors is returned, in the order of the constructor
		declaration.

		If `e` is `null`, the result is unspecified.</haxe_doc>
		</createAll>
		<getConstructors public="1" params="T" get="inline" set="null" line="108" static="1">
			<f a="e">
				<x path="Enum"><c path="getConstructors.T"/></x>
				<c path="Array"><c path="String"/></c>
			</f>
			<haxe_doc>Returns a list of the names of all constructors of enum `e`.

		The order of the constructor names in the returned Array is preserved
		from the original syntax.

		If `c` is `null`, the result is unspecified.</haxe_doc>
		</getConstructors>
		<haxe_doc>This class provides advanced methods on enums. It is ideally used with
	`using EnumTools` and then acts as an 
  [extension](https://haxe.org/manual/lf-static-extension.html) to the 
  `enum` types.

	If the first argument to any of the methods is null, the result is
	unspecified.</haxe_doc>
	</class>
	<class path="haxe.EnumValueTools" params="" file="/usr/lib/haxe/std/haxe/EnumTools.hx" module="haxe.EnumTools" extern="1">
		<equals public="1" params="T" get="inline" set="null" line="132" static="1">
			<f a="a:b">
				<c path="equals.T"/>
				<c path="equals.T"/>
				<x path="Bool"/>
			</f>
			<haxe_doc>Recursively compares two enum instances `a` and `b` by value.

		Unlike `a == b`, this function performs a deep equality check on the
		arguments of the constructors (if there are any).

		If `a` or `b` are `null`, the result is unspecified.</haxe_doc>
		</equals>
		<getName public="1" get="inline" set="null" line="143" static="1">
			<f a="e">
				<x path="EnumValue"/>
				<c path="String"/>
			</f>
			<haxe_doc>Returns the constructor name of enum instance `e`.

		The result String does not contain any constructor arguments.

		If `e` is `null`, the result is unspecified.</haxe_doc>
		</getName>
		<getParameters public="1" get="inline" set="null" line="157" static="1">
			<f a="e">
				<x path="EnumValue"/>
				<c path="Array"><d/></c>
			</f>
			<haxe_doc>Returns a list of the constructor arguments of enum instance `e`.

		If `e` has no arguments, the result is `[]`.

		Otherwise the result are the values that were used as arguments to `e`,
		in the order of their declaration.

		If `e` is `null`, the result is unspecified.</haxe_doc>
		</getParameters>
		<getIndex public="1" get="inline" set="null" line="169" static="1">
			<f a="e">
				<x path="EnumValue"/>
				<x path="Int"/>
			</f>
			<haxe_doc>Returns the index of enum instance `e`.

		This corresponds to the original syntactic position of `e`. The index of
		the first declared constructor is 0, the next one is 1 etc.

		If `e` is `null`, the result is unspecified.</haxe_doc>
		</getIndex>
		<match public="1" set="method" static="1">
			<f a="e:pattern">
				<x path="EnumValue"/>
				<d/>
				<x path="Bool"/>
			</f>
			<haxe_doc>Matches enum instance `e` against pattern `pattern`, returning `true` if
		matching succeeded and `false` otherwise.

		Example usage:

		```haxe
		if (e.match(pattern)) {
			// codeIfTrue
		} else {
			// codeIfFalse
		}
		```

		This is equivalent to the following code:

		```haxe
		switch (e) {
			case pattern:
				// codeIfTrue
			case _:
				// codeIfFalse
		}
		```

		This method is implemented in the compiler. This definition exists only
		for documentation.</haxe_doc>
		</match>
		<haxe_doc>This class provides advanced methods on enum values. It is ideally used with
	`using EnumValueTools` and then acts as an 
  [extension](https://haxe.org/manual/lf-static-extension.html) to the 
  `EnumValue` types.

	If the first argument to any of the methods is null, the result is
	unspecified.</haxe_doc>
	</class>
	<abstract path="haxe.ds.HashMap" params="K:V" file="/usr/lib/haxe/std/haxe/ds/HashMap.hx">
		<this><c path="haxe.ds._HashMap.HashMapData">
	<c path="haxe.ds.HashMap.K"/>
	<c path="haxe.ds.HashMap.V"/>
</c></this>
		<haxe_doc>HashMap allows mapping of hashable objects to arbitrary values.

	See `Map` for documentation details.

	@see https://haxe.org/manual/std-Map.html</haxe_doc>
		<impl><class path="haxe.ds._HashMap.HashMap_Impl_" params="" file="/usr/lib/haxe/std/haxe/ds/HashMap.hx" private="1" module="haxe.ds.HashMap"><meta>
	<m n=":keep"/>
	<m n=":final"/>
</meta></class></impl>
	</abstract>
	<class path="haxe.ds.IntMap" params="T" file="/usr/lib/haxe/std/haxe/ds/IntMap.hx" extern="1">
		<implements path="haxe.IMap">
			<x path="Int"/>
			<c path="haxe.ds.IntMap.T"/>
		</implements>
		<set public="1" set="method">
			<f a="key:value">
				<x path="Int"/>
				<c path="haxe.ds.IntMap.T"/>
				<x path="Void"/>
			</f>
			<haxe_doc>See `Map.set`</haxe_doc>
		</set>
		<get public="1" set="method">
			<f a="key">
				<x path="Int"/>
				<t path="Null"><c path="haxe.ds.IntMap.T"/></t>
			</f>
			<haxe_doc>See `Map.get`</haxe_doc>
		</get>
		<exists public="1" set="method">
			<f a="key">
				<x path="Int"/>
				<x path="Bool"/>
			</f>
			<haxe_doc>See `Map.exists`</haxe_doc>
		</exists>
		<remove public="1" set="method">
			<f a="key">
				<x path="Int"/>
				<x path="Bool"/>
			</f>
			<haxe_doc>See `Map.remove`</haxe_doc>
		</remove>
		<keys public="1" set="method">
			<f a=""><t path="Iterator"><x path="Int"/></t></f>
			<haxe_doc>See `Map.keys`</haxe_doc>
		</keys>
		<iterator public="1" set="method">
			<f a=""><t path="Iterator"><c path="haxe.ds.IntMap.T"/></t></f>
			<haxe_doc>See `Map.iterator`</haxe_doc>
		</iterator>
		<toString public="1" set="method">
			<f a=""><c path="String"/></f>
			<haxe_doc>See `Map.toString`</haxe_doc>
		</toString>
		<new public="1" set="method">
			<f a=""><x path="Void"/></f>
			<haxe_doc>Creates a new IntMap.</haxe_doc>
		</new>
		<haxe_doc>IntMap allows mapping of Int keys to arbitrary values.

	See `Map` for documentation details.

	@see https://haxe.org/manual/std-Map.html</haxe_doc>
	</class>
	<class path="haxe.ds.ObjectMap" params="K:V" file="/usr/lib/haxe/std/haxe/ds/ObjectMap.hx" extern="1">
		<implements path="haxe.IMap">
			<c path="haxe.ds.ObjectMap.K"/>
			<c path="haxe.ds.ObjectMap.V"/>
		</implements>
		<set public="1" set="method">
			<f a="key:value">
				<c path="haxe.ds.ObjectMap.K"/>
				<c path="haxe.ds.ObjectMap.V"/>
				<x path="Void"/>
			</f>
			<haxe_doc>See `Map.set`</haxe_doc>
		</set>
		<get public="1" set="method">
			<f a="key">
				<c path="haxe.ds.ObjectMap.K"/>
				<t path="Null"><c path="haxe.ds.ObjectMap.V"/></t>
			</f>
			<haxe_doc>See `Map.get`</haxe_doc>
		</get>
		<exists public="1" set="method">
			<f a="key">
				<c path="haxe.ds.ObjectMap.K"/>
				<x path="Bool"/>
			</f>
			<haxe_doc>See `Map.exists`</haxe_doc>
		</exists>
		<remove public="1" set="method">
			<f a="key">
				<c path="haxe.ds.ObjectMap.K"/>
				<x path="Bool"/>
			</f>
			<haxe_doc>See `Map.remove`</haxe_doc>
		</remove>
		<keys public="1" set="method">
			<f a=""><t path="Iterator"><c path="haxe.ds.ObjectMap.K"/></t></f>
			<haxe_doc>See `Map.keys`</haxe_doc>
		</keys>
		<iterator public="1" set="method">
			<f a=""><t path="Iterator"><c path="haxe.ds.ObjectMap.V"/></t></f>
			<haxe_doc>See `Map.iterator`</haxe_doc>
		</iterator>
		<toString public="1" set="method">
			<f a=""><c path="String"/></f>
			<haxe_doc>See `Map.toString`</haxe_doc>
		</toString>
		<new public="1" set="method">
			<f a=""><x path="Void"/></f>
			<haxe_doc>Creates a new ObjectMap.</haxe_doc>
		</new>
		<haxe_doc>ObjectMap allows mapping of object keys to arbitrary values.

	On static targets, the keys are considered to be strong references. Refer
	to `haxe.ds.WeakMap` for a weak reference version.

	See `Map` for documentation details.

	@see https://haxe.org/manual/std-Map.html</haxe_doc>
	</class>
	<class path="haxe.ds.StringMap" params="T" file="/usr/lib/haxe/std/haxe/ds/StringMap.hx" extern="1">
		<implements path="haxe.IMap">
			<c path="String"/>
			<c path="haxe.ds.StringMap.T"/>
		</implements>
		<set public="1" set="method">
			<f a="key:value">
				<c path="String"/>
				<c path="haxe.ds.StringMap.T"/>
				<x path="Void"/>
			</f>
			<haxe_doc>See `Map.set`</haxe_doc>
		</set>
		<get public="1" set="method">
			<f a="key">
				<c path="String"/>
				<t path="Null"><c path="haxe.ds.StringMap.T"/></t>
			</f>
			<haxe_doc>See `Map.get`</haxe_doc>
		</get>
		<exists public="1" set="method">
			<f a="key">
				<c path="String"/>
				<x path="Bool"/>
			</f>
			<haxe_doc>See `Map.exists`</haxe_doc>
		</exists>
		<remove public="1" set="method">
			<f a="key">
				<c path="String"/>
				<x path="Bool"/>
			</f>
			<haxe_doc>See `Map.remove`</haxe_doc>
		</remove>
		<keys public="1" set="method">
			<f a=""><t path="Iterator"><c path="String"/></t></f>
			<haxe_doc>See `Map.keys`</haxe_doc>
		</keys>
		<iterator public="1" set="method">
			<f a=""><t path="Iterator"><c path="haxe.ds.StringMap.T"/></t></f>
			<haxe_doc>See `Map.iterator`</haxe_doc>
		</iterator>
		<toString public="1" set="method">
			<f a=""><c path="String"/></f>
			<haxe_doc>See `Map.toString`</haxe_doc>
		</toString>
		<new public="1" set="method">
			<f a=""><x path="Void"/></f>
			<haxe_doc>Creates a new StringMap.</haxe_doc>
		</new>
		<haxe_doc>StringMap allows mapping of String keys to arbitrary values.

	See `Map` for documentation details.

	@see https://haxe.org/manual/std-Map.html</haxe_doc>
		<meta><m n=":directlyUsed"/></meta>
	</class>
	<class path="haxe.xml._Parser.S" params="" file="/usr/lib/haxe/std/haxe/xml/Parser.hx" private="1" module="haxe.xml.Parser" extern="1">
		<IGNORE_SPACES public="1" get="inline" set="null" expr="0" line="28" static="1">
			<x path="Int"/>
			<meta><m n=":value"><e>0</e></m></meta>
		</IGNORE_SPACES>
		<BEGIN public="1" get="inline" set="null" expr="1" line="29" static="1">
			<x path="Int"/>
			<meta><m n=":value"><e>1</e></m></meta>
		</BEGIN>
		<BEGIN_NODE public="1" get="inline" set="null" expr="2" line="30" static="1">
			<x path="Int"/>
			<meta><m n=":value"><e>2</e></m></meta>
		</BEGIN_NODE>
		<TAG_NAME public="1" get="inline" set="null" expr="3" line="31" static="1">
			<x path="Int"/>
			<meta><m n=":value"><e>3</e></m></meta>
		</TAG_NAME>
		<BODY public="1" get="inline" set="null" expr="4" line="32" static="1">
			<x path="Int"/>
			<meta><m n=":value"><e>4</e></m></meta>
		</BODY>
		<ATTRIB_NAME public="1" get="inline" set="null" expr="5" line="33" static="1">
			<x path="Int"/>
			<meta><m n=":value"><e>5</e></m></meta>
		</ATTRIB_NAME>
		<EQUALS public="1" get="inline" set="null" expr="6" line="34" static="1">
			<x path="Int"/>
			<meta><m n=":value"><e>6</e></m></meta>
		</EQUALS>
		<ATTVAL_BEGIN public="1" get="inline" set="null" expr="7" line="35" static="1">
			<x path="Int"/>
			<meta><m n=":value"><e>7</e></m></meta>
		</ATTVAL_BEGIN>
		<ATTRIB_VAL public="1" get="inline" set="null" expr="8" line="36" static="1">
			<x path="Int"/>
			<meta><m n=":value"><e>8</e></m></meta>
		</ATTRIB_VAL>
		<CHILDS public="1" get="inline" set="null" expr="9" line="37" static="1">
			<x path="Int"/>
			<meta><m n=":value"><e>9</e></m></meta>
		</CHILDS>
		<CLOSE public="1" get="inline" set="null" expr="10" line="38" static="1">
			<x path="Int"/>
			<meta><m n=":value"><e>10</e></m></meta>
		</CLOSE>
		<WAIT_END public="1" get="inline" set="null" expr="11" line="39" static="1">
			<x path="Int"/>
			<meta><m n=":value"><e>11</e></m></meta>
		</WAIT_END>
		<WAIT_END_RET public="1" get="inline" set="null" expr="12" line="40" static="1">
			<x path="Int"/>
			<meta><m n=":value"><e>12</e></m></meta>
		</WAIT_END_RET>
		<PCDATA public="1" get="inline" set="null" expr="13" line="41" static="1">
			<x path="Int"/>
			<meta><m n=":value"><e>13</e></m></meta>
		</PCDATA>
		<HEADER public="1" get="inline" set="null" expr="14" line="42" static="1">
			<x path="Int"/>
			<meta><m n=":value"><e>14</e></m></meta>
		</HEADER>
		<COMMENT public="1" get="inline" set="null" expr="15" line="43" static="1">
			<x path="Int"/>
			<meta><m n=":value"><e>15</e></m></meta>
		</COMMENT>
		<DOCTYPE public="1" get="inline" set="null" expr="16" line="44" static="1">
			<x path="Int"/>
			<meta><m n=":value"><e>16</e></m></meta>
		</DOCTYPE>
		<CDATA public="1" get="inline" set="null" expr="17" line="45" static="1">
			<x path="Int"/>
			<meta><m n=":value"><e>17</e></m></meta>
		</CDATA>
		<ESCAPE public="1" get="inline" set="null" expr="18" line="46" static="1">
			<x path="Int"/>
			<meta><m n=":value"><e>18</e></m></meta>
		</ESCAPE>
	</class>
	<class path="haxe.xml.XmlParserException" params="" file="/usr/lib/haxe/std/haxe/xml/Parser.hx" module="haxe.xml.Parser">
		<message public="1">
			<c path="String"/>
			<haxe_doc>* the XML parsing error message</haxe_doc>
		</message>
		<lineNumber public="1">
			<x path="Int"/>
			<haxe_doc>* the line number at which the XML parsing error occured</haxe_doc>
		</lineNumber>
		<positionAtLine public="1">
			<x path="Int"/>
			<haxe_doc>* the character position in the reported line at which the parsing error occured</haxe_doc>
		</positionAtLine>
		<position public="1">
			<x path="Int"/>
			<haxe_doc>* the character position in the XML string at which the parsing error occured</haxe_doc>
		</position>
		<xml public="1">
			<c path="String"/>
			<haxe_doc>* the invalid XML string</haxe_doc>
		</xml>
		<toString public="1" set="method" line="96"><f a=""><c path="String"/></f></toString>
		<new public="1" set="method" line="76"><f a="message:xml:position">
	<c path="String"/>
	<c path="String"/>
	<x path="Int"/>
	<x path="Void"/>
</f></new>
		<meta>
			<m n=":keep"/>
			<m n=":directlyUsed"/>
		</meta>
	</class>
	<class path="haxe.xml.Parser" params="" file="/usr/lib/haxe/std/haxe/xml/Parser.hx">
		<escapes line="104" static="1"><c path="haxe.ds.StringMap"><c path="String"/></c></escapes>
		<parse public="1" set="method" line="119" static="1">
			<f a="str:?strict">
				<c path="String"/>
				<x path="Bool"/>
				<c path="Xml"/>
			</f>
			<haxe_doc>* Parses the String into an XML Document. Set strict parsing to true in order to enable a strict check of XML attributes and entities.
	 *
	 * @throws haxe.xml.XmlParserException</haxe_doc>
		</parse>
		<doParse set="method" line="126" static="1"><f a="str:strict:?p:?parent">
	<c path="String"/>
	<x path="Bool"/>
	<x path="Int"/>
	<c path="Xml"/>
	<x path="Int"/>
</f></doParse>
		<meta>
			<m n=":keep"/>
			<m n=":directlyUsed"/>
		</meta>
	</class>
</haxe>